psydk/psydk.abi3.so
psydk/__init__.py
psydk-0.1.4.dist-info/RECORD
psydk-0.1.4.dist-info/WHEEL
psydk-0.1.4.dist-info/METADATA
