Metadata-Version: 2.4
Name: psydk
Version: 0.1.4
Classifier: Programming Language :: Rust
Classifier: Programming Language :: Python :: Implementation :: CPython
Classifier: Programming Language :: Python :: Implementation :: PyPy
Summary: Python bindings for psydk
Keywords: psychophysics,psychology,experiments,stimuli,perception
Author: Marc Pabst
Author-email: Marc Pabst <mail@xxxxxxx.com>
License: MPL-2.0
Requires-Python: >=3.10
Project-URL: Source Code, https://github.com/marcpabst/psydk
